alis/__init__.py
alis/__main__.py
alis/alis.sh
alis_tool-0.0.15.dist-info/METADATA
alis_tool-0.0.15.dist-info/WHEEL
alis_tool-0.0.15.dist-info/entry_points.txt
alis_tool-0.0.15.dist-info/top_level.txt
alis_tool-0.0.15.dist-info/RECORD
