Metadata-Version: 2.1
Name: alis-tool
Version: 0.0.15
Summary: ALIS (Arch Linux Installer Script)
Home-page: https://gitlab.com/Inonut/alis
Author: Dragos Raducanu
Author-email: raducanudragos12@gmail.com
License: UNKNOWN
Platform: UNKNOWN
Classifier: Programming Language :: Python :: 3
Classifier: Operating System :: POSIX :: Linux
Requires-Python: >=3.6
